[
	{
		"category":"",
		"country":{
			"code":"",
			"name":""
		},
		"language":{
			"code":"",
			"name":""
		},
		"logo":"https://i.imgur.com/UmHcfW0.jpg",
		"name":"IPL2021",
		"status":"GOOD",
		"tvg":{
			"id":"",
			"name":"",
			"url":""
		},
		"url":"https://media.publit.io/file/20210411215318257.gif"
	},
	{
		"category":"",
		"country":{
			"code":"",
			"name":""
		},
		"language":{
			"code":"",
			"name":""
		},
		"logo":"https://i.imgur.com/8FaT8z8.jpg",
		"name":"StarSports2HD",
		"status":"GOOD",
		"tvg":{
			"id":"",
			"name":"",
			"url":""
		},
		"url":"http://221.120.204.4/STAR-SPORTS-2/tracks-v1a1/mono.m3u8"
	},
	{
		"category":"",
		"country":{
			"code":"",
			"name":""
		},
		"language":{
			"code":"",
			"name":""
		},
		"logo":"https://i.imgur.com/ylOJCnR.jpg",
		"name":"StarSportsSelect1HD",
		"status":"GOOD",
		"tvg":{
			"id":"",
			"name":"",
			"url":""
		},
		"url":"http://221.120.204.4/STAR-SPORTS-SELECT-1-/tracks-v1a1/mono.m3u8"
	}
]
